{
  "id": "20p5-kQXF_Q",
  "title": "What does the next training paradigm look like?",
  "channel": "Dwarkesh Patel",
  "channelUrl": "https://www.youtube.com/@DwarkeshPatel",
  "published": "2026-06-26T16:56:10+00:00",
  "kind": "opinion",
  "recommended": false,
  "summary": "Dwarkesh Patel discusses the next generation of AI training paradigms beyond standard supervised learning. The essay explores concepts like grindability, verifiability, reinforcement learning with verification (RLVR), test-time scaling, and dreaming as potential directions for future model training.",
  "writeup": "Dwarkesh Patel examines what AI training could look like after standard supervised learning. The essay works through grindability, verifiability, reinforcement learning with verification (RLVR), test-time scaling, and dreaming as candidate directions for future model training. The framing matters because it organizes proposed post-supervised methods around whether tasks can be ground out and whether their outputs can be verified.",
  "wh": "4c6d2b5126d8abab",
  "concepts": [
    {
      "slug": "reinforcement-learning",
      "label": "reinforcement learning"
    },
    {
      "slug": "test-time-compute",
      "label": "test-time compute"
    },
    {
      "slug": "grindability",
      "label": "grindability"
    },
    {
      "slug": "verifiability",
      "label": "verifiability"
    },
    {
      "slug": "dreaming",
      "label": "dreaming"
    }
  ],
  "similar": [
    {
      "id": "y9eGsI2C9iY",
      "title": "Why Inventing General Relativity Is the Final Test for AI - Adam Brown",
      "channel": "Dwarkesh Patel",
      "score": 0.615
    },
    {
      "id": "mGYr9VqQnEI",
      "title": "Harness Engineering Is AI’s New Gold Rush",
      "channel": "AI Revolution",
      "score": 0.607
    },
    {
      "id": "jxHIw_OA8_I",
      "title": "Stop perfecting your prompt. Do this instead",
      "channel": "Jeff Su",
      "score": 0.606
    },
    {
      "id": "4pG3SJQPAwk",
      "title": "The data black hole at the center of AI",
      "channel": "Dwarkesh Patel",
      "score": 0.6
    },
    {
      "id": "p7t1Q_p2gZs",
      "title": "AI Pioneer Geoffrey Hinton: AI Is Conscious, Superintelligence is Coming, And We Should Be Worried",
      "channel": "Alex Kantrowitz",
      "score": 0.584
    },
    {
      "id": "4wMRXmLpdA8",
      "title": "AI in the SDLC: Rethinking AI Coding Tools & AI Agents",
      "channel": "IBM Technology",
      "score": 0.579
    }
  ]
}
