{
  "id": "6C0FjHoN3qE",
  "title": "Google Antigravity 2.0 Beginner's Guide",
  "channel": "Google Antigravity",
  "channelUrl": "https://www.youtube.com/@googleantigravity",
  "published": "2026-05-19T17:47:28+00:00",
  "kind": "tool",
  "recommended": false,
  "summary": "Google Antigravity 2.0 is a desktop application for agent-optimized workflows. It provides multi-agent team capabilities, scheduled task management, native voice support, and integration with other Google products.",
  "writeup": "",
  "wh": "c45d26079a32ec53",
  "concepts": [
    {
      "slug": "multi-agent-systems",
      "label": "multi-agent systems"
    },
    {
      "slug": "agent-orchestration",
      "label": "agent orchestration"
    },
    {
      "slug": "voice-interface",
      "label": "voice interface"
    }
  ],
  "similar": [
    {
      "id": "am0lg5-ofvQ",
      "title": "Google Antigravity CLI Full Walkthrough",
      "channel": "Google Antigravity",
      "score": 0.714
    },
    {
      "id": "1rF_SZZ3yWs",
      "title": "How marketers are using Google Antigravity",
      "channel": "Google Antigravity",
      "score": 0.712
    },
    {
      "id": "WiWDrTujl_w",
      "title": "FIRST LOOK into Google Antigravity CLI",
      "channel": "Google Antigravity",
      "score": 0.702
    },
    {
      "id": "RGhunHLnVIg",
      "title": "Announcing Google Antigravity SDK",
      "channel": "Google Antigravity",
      "score": 0.689
    },
    {
      "id": "ztLYODplhrw",
      "title": "Google Bans Coding With Its Biggest Attack On Devs Ever: AntiGravity 2.0",
      "channel": "AI Revolution",
      "score": 0.627
    },
    {
      "id": "C8Ch-l7PZe0",
      "title": "Mission Report Ep. 04 | Antigravity Updates",
      "channel": "Google Antigravity",
      "score": 0.599
    }
  ]
}
