{
  "id": "92LvgAcR6fI",
  "title": "What's new with Gemini from Google DeepMind",
  "channel": "Google Cloud Tech",
  "channelUrl": "https://www.youtube.com/@googlecloudtech",
  "published": "2026-06-25T16:32:26+00:00",
  "kind": "tool",
  "recommended": false,
  "summary": "Google DeepMind released Gemini 3 with upgraded model reasoning, expanded context window processing, and enhanced multimodal tool use. The model is deployed in Vertex AI and designed to support agentic applications and developer workflows.",
  "writeup": "This video details Google DeepMind's latest Gemini upgrades: stronger model reasoning, expanded context windows, and improved multimodal tool use. The changes matter because they support agentic applications in Vertex AI, tying model improvements to deployable workflows. Concrete takeaways include the connection between expanded context and tool use, and research advances in agent design that underpin these agentic capabilities.",
  "wh": "e3c4c36f866a0ca7",
  "concepts": [
    {
      "slug": "multi-agent-systems",
      "label": "multi-agent systems"
    },
    {
      "slug": "conversational-ai",
      "label": "conversational AI"
    },
    {
      "slug": "workspace-expansion",
      "label": "workspace expansion"
    },
    {
      "slug": "tool-use",
      "label": "tool use"
    }
  ],
  "similar": [
    {
      "id": "6VV5Gvmtrl4",
      "title": "What’s new in Gemma 4?",
      "channel": "Google DeepMind",
      "score": 0.777
    },
    {
      "id": "J02-39xtlt4",
      "title": "Google strikes back! Gemini Omni, AI glasses, new models",
      "channel": "AI Search",
      "score": 0.773
    },
    {
      "id": "R6mM0m3IZWY",
      "title": "Gemini 3.5 Flash has landed.",
      "channel": "Google DeepMind",
      "score": 0.763
    },
    {
      "id": "AEH6dBOnE_U",
      "title": "This is Gemini Omni ♾️ #GoogleIO",
      "channel": "Google DeepMind",
      "score": 0.734
    },
    {
      "id": "kn9Gh5HWqQs",
      "title": "NEW Gemini Features Explained — How to Use Google’s Latest AI Upgrade",
      "channel": "AI Master",
      "score": 0.717
    },
    {
      "id": "pm5PBbo6l2k",
      "title": "Gemini for Science is here. 🧬",
      "channel": "Google DeepMind",
      "score": 0.716
    }
  ]
}
