{
  "id": "9VmJewRHL7s",
  "title": "Why Italians Saw the Pope Very Differently - Ada Palmer",
  "channel": "Dwarkesh Patel",
  "channelUrl": "https://www.youtube.com/@DwarkeshPatel",
  "published": "2026-06-23T18:47:59+00:00",
  "kind": "opinion",
  "recommended": false,
  "summary": "This is a historical commentary by Ada Palmer on how Italian perspectives on papal authority differed from other regions. The discussion explores divergent views and cultural contexts around religious leadership in Italian history.",
  "writeup": "Historian Ada Palmer examines how Italians viewed papal authority differently from other regions, drawing on the distinct cultural and historical contexts shaping those perspectives. The conversation centers on why religious leadership was understood in divergent ways across Italian history. The takeaway: perception of the papacy was regionally contingent, with Italian attitudes diverging from those held elsewhere.",
  "wh": "2368cf69ec52397c",
  "concepts": [],
  "similar": [
    {
      "id": "U1FrhkLQnCI",
      "title": "Machiavelli is the most misunderstood thinker of all time – Ada Palmer",
      "channel": "Dwarkesh Patel",
      "score": 0.558
    },
    {
      "id": "HoMvCjnpAJ8",
      "title": "Breaking Down the Pope's AI Essay",
      "channel": "Matthew Berman",
      "score": 0.55
    },
    {
      "id": "H0Tgz9Nnx2s",
      "title": "The strangest riot in papal history - Ada Palmer",
      "channel": "Dwarkesh Patel",
      "score": 0.537
    },
    {
      "id": "IsWr9Lir8Pc",
      "title": "They loved Trajan so much they rewrote the afterlife for him - Ada Palmer",
      "channel": "Dwarkesh Patel",
      "score": 0.525
    },
    {
      "id": "Sis-TKTV6xw",
      "title": "The Real Reason Giordano Bruno Was Burned at the Stake - Ada Palmer",
      "channel": "Dwarkesh Patel",
      "score": 0.493
    },
    {
      "id": "z5BkwnEBw8I",
      "title": "The historical trap Putin can't escape - Sarah Paine",
      "channel": "Dwarkesh Patel",
      "score": 0.444
    }
  ]
}
