{
  "id": "_GljcHROPX8",
  "title": "What happens when agents get their own computers",
  "channel": "Cursor",
  "channelUrl": "https://www.youtube.com/@cursor_ai",
  "published": "2026-05-12T17:20:09+00:00",
  "kind": "tool",
  "recommended": false,
  "summary": "Cursor 3 introduces agent capabilities that automate testing and deployment workflows. Agents can write code, run tests independently, generate video proof of execution, and manage pull request merging without human intervention. The platform provides an agents-first interface and primitives for building custom agent systems.",
  "writeup": "",
  "wh": "5464add78f333530",
  "concepts": [
    {
      "slug": "ai-agents",
      "label": "AI agents"
    },
    {
      "slug": "testing",
      "label": "testing"
    },
    {
      "slug": "code-generation",
      "label": "code generation"
    },
    {
      "slug": "workflow-automation",
      "label": "workflow automation"
    },
    {
      "slug": "human-in-the-loop",
      "label": "human-in-the-loop"
    }
  ],
  "similar": [
    {
      "id": "UxbULt_hCdA",
      "title": "Introducing Cursor 3",
      "channel": "Cursor",
      "score": 0.695
    },
    {
      "id": "8h9j2rskP14",
      "title": "The next era of AI coding",
      "channel": "Cursor",
      "score": 0.653
    },
    {
      "id": "-jnwTZ789V0",
      "title": "Running 128 Coding Agents at Once",
      "channel": "Cursor",
      "score": 0.628
    },
    {
      "id": "blgUmyMiROI",
      "title": "How are coding agents changing software engineering?",
      "channel": "Cursor",
      "score": 0.606
    },
    {
      "id": "dJAVS1g3NDw",
      "title": "How Cursor builds agentic workflows across the SDLC",
      "channel": "Cursor",
      "score": 0.605
    },
    {
      "id": "2zhchG0r6iI",
      "title": "Okay, this unleashed my agent",
      "channel": "AI Jason",
      "score": 0.599
    }
  ]
}
