{
  "id": "EF1BFaNZN9U",
  "title": "SynthID, our imperceptible watermark for AI-generated content, is expanding to more partners.",
  "channel": "Google DeepMind",
  "channelUrl": "https://www.youtube.com/@googledeepmind",
  "published": "2026-05-22T16:09:49+00:00",
  "kind": "tool",
  "recommended": false,
  "summary": "SynthID is an imperceptible watermark technology for AI-generated content developed by Google DeepMind. The tool is expanding to additional partners for broader adoption.",
  "writeup": "",
  "wh": "373c3c91adb3e041",
  "concepts": [
    {
      "slug": "watermarking",
      "label": "watermarking"
    },
    {
      "slug": "synthetic-data",
      "label": "synthetic data"
    }
  ],
  "similar": [
    {
      "id": "R6mM0m3IZWY",
      "title": "Gemini 3.5 Flash has landed.",
      "channel": "Google DeepMind",
      "score": 0.606
    },
    {
      "id": "u3T_0HmNbHM",
      "title": "Build your next story with Gemini Omni.",
      "channel": "Google DeepMind",
      "score": 0.602
    },
    {
      "id": "92LvgAcR6fI",
      "title": "What's new with Gemini from Google DeepMind",
      "channel": "Google Cloud Tech",
      "score": 0.596
    },
    {
      "id": "YiIrnYalHS4",
      "title": "Google’s New AI Just Broke The AI Speed Limit: DiffusionGemma",
      "channel": "AI Revolution",
      "score": 0.596
    },
    {
      "id": "Dxn3BcSgsMY",
      "title": "1,000+ Tokens/Sec: Google Just Shattered the AI Speed Limit (DiffusionGemma)",
      "channel": "Better Stack",
      "score": 0.591
    },
    {
      "id": "quxnhOeRz7I",
      "title": "Self-evolving AI, robot fights, new GPT voice, new local image model, Gemma upgrade: AI NEWS",
      "channel": "AI Search",
      "score": 0.591
    }
  ]
}
