{
  "id": "k7HrSreatII",
  "title": "GPU-accelerated virtual drug screening with cuML and Agent Platform",
  "channel": "Google Cloud Tech",
  "channelUrl": "https://www.youtube.com/@googlecloudtech",
  "published": "2026-06-09T16:57:57+00:00",
  "kind": "tool",
  "recommended": false,
  "summary": "Google Cloud and NVIDIA demonstrated GPU-accelerated virtual drug screening for molecular binding prediction at scale. The approach uses cuDF and cuML to achieve 20x-45x training speedups on tabular data without modifying pandas or scikit-learn code, applied to billion-molecule screening for lung cancer targets like EGFR.",
  "writeup": "Google Cloud Tech walks through a joint Google Cloud and NVIDIA demonstration of GPU-accelerated virtual drug screening for molecular binding prediction at scale. The setup pairs cuDF and cuML to reach 20x-45x training speedups on tabular data without changes to existing pandas or scikit-learn code, then applies the workflow to billion-molecule screening against lung cancer targets such as EGFR. The takeaway: drop-in GPU acceleration of standard tabular ML libraries can compress training time enough to make screening at that volume practical.",
  "wh": "3f0614871a8c5f93",
  "concepts": [
    {
      "slug": "gpu-acceleration",
      "label": "GPU acceleration"
    },
    {
      "slug": "cuml",
      "label": "cuML"
    },
    {
      "slug": "cudf",
      "label": "cuDF"
    },
    {
      "slug": "drug-discovery",
      "label": "drug discovery"
    },
    {
      "slug": "tabular-ml",
      "label": "tabular ML"
    },
    {
      "slug": "nvidia",
      "label": "NVIDIA"
    }
  ],
  "similar": [
    {
      "id": "v0eokiSJO74",
      "title": "From Genetic Variant to Wet-lab: Accelerating the path from hypothesis to experiment",
      "channel": "Google Antigravity",
      "score": 0.596
    },
    {
      "id": "exh1vwGlrSo",
      "title": "Understanding cancer at a genetic level with AI",
      "channel": "Google DeepMind",
      "score": 0.534
    },
    {
      "id": "s3rNDndvav0",
      "title": "The biggest AI breakthrough in medicine & drug discovery",
      "channel": "AI Search",
      "score": 0.528
    },
    {
      "id": "Cnuj24PjWrQ",
      "title": "Using AI to outsmart drug-resistant bacteria",
      "channel": "Google DeepMind",
      "score": 0.526
    },
    {
      "id": "zDGHt0LB-dA",
      "title": "GPU Cloud Deployment Without Leaving Your IDE — Audry Hsu, RunPod",
      "channel": "AI Engineer",
      "score": 0.521
    },
    {
      "id": "SS-A8sE7hkw",
      "title": "Sovereign Escape Velocity: Ownership w Open Models — Gus Martins, & Ian Ballantyne, Google DeepMind",
      "channel": "AI Engineer",
      "score": 0.512
    }
  ]
}
