{
  "kind": "opinion",
  "horizon": "month",
  "generated": "2026-06-18",
  "synthetic": false,
  "entities": [
    {
      "id": "ai-agents",
      "label": "AI agents",
      "attention": 201,
      "delta": 164.3,
      "sparkline": [
        103,
        104,
        103,
        96,
        94,
        93,
        91,
        87
      ]
    },
    {
      "id": "test-time-compute",
      "label": "test-time compute",
      "attention": 133,
      "delta": 82.2,
      "sparkline": [
        57,
        66,
        61,
        62,
        58,
        63,
        59,
        59
      ]
    },
    {
      "id": "code-generation",
      "label": "code generation",
      "attention": 83,
      "delta": 70.4,
      "sparkline": [
        40,
        37,
        35,
        32,
        34,
        44,
        41,
        41
      ]
    },
    {
      "id": "ai-safety",
      "label": "AI safety",
      "attention": 73,
      "delta": 62.8,
      "sparkline": [
        38,
        41,
        39,
        37,
        42,
        40,
        39,
        41
      ]
    },
    {
      "id": "model-evaluation",
      "label": "model evaluation",
      "attention": 57,
      "delta": 49.1,
      "sparkline": [
        29,
        28,
        26,
        24,
        22,
        21,
        21,
        23
      ]
    },
    {
      "id": "prompt-engineering",
      "label": "prompt engineering",
      "attention": 57,
      "delta": 30.8,
      "sparkline": [
        24,
        23,
        26,
        24,
        23,
        21,
        22,
        20
      ]
    },
    {
      "id": "large-language-models",
      "label": "large language models",
      "attention": 42,
      "delta": 21.9,
      "sparkline": [
        23,
        22,
        20,
        19,
        18,
        17,
        20,
        20
      ]
    },
    {
      "id": "multimodal-learning",
      "label": "multimodal learning",
      "attention": 42,
      "delta": 26,
      "sparkline": [
        19,
        22,
        21,
        19,
        18,
        17,
        16,
        15
      ]
    },
    {
      "id": "agi",
      "label": "AGI",
      "attention": 41,
      "delta": 41.2,
      "sparkline": [
        18,
        17,
        16,
        14,
        15,
        19,
        18,
        16
      ]
    },
    {
      "id": "local-inference",
      "label": "local inference",
      "attention": 40,
      "delta": 23.3,
      "sparkline": [
        10,
        10,
        14,
        19,
        17,
        26,
        27,
        26
      ]
    },
    {
      "id": "agentic-workflows",
      "label": "agentic workflows",
      "attention": 40,
      "delta": 21.7,
      "sparkline": [
        24,
        22,
        21,
        19,
        18,
        17,
        18,
        19
      ]
    },
    {
      "id": "generative-ai",
      "label": "generative AI",
      "attention": 32,
      "delta": 17.8,
      "sparkline": [
        12,
        16,
        15,
        14,
        13,
        12,
        13,
        14
      ]
    },
    {
      "id": "video-generation",
      "label": "video generation",
      "attention": 31,
      "delta": 15.9,
      "sparkline": [
        13,
        12,
        12,
        16,
        15,
        14,
        17,
        16
      ]
    },
    {
      "id": "agent-orchestration",
      "label": "agent orchestration",
      "attention": 31,
      "delta": 26.8,
      "sparkline": [
        17,
        20,
        19,
        17,
        16,
        15,
        14,
        13
      ]
    },
    {
      "id": "enterprise-ai",
      "label": "enterprise AI",
      "attention": 30,
      "delta": 24.8,
      "sparkline": [
        11,
        10,
        14,
        13,
        14,
        14,
        19,
        19
      ]
    },
    {
      "id": "foundation-models",
      "label": "foundation models",
      "attention": 26,
      "delta": 24.3,
      "sparkline": [
        9,
        8,
        7,
        7,
        6,
        11,
        14,
        17
      ]
    }
  ]
}
