{
  "kind": "technique",
  "horizon": "month",
  "generated": "2026-06-07",
  "synthetic": false,
  "entities": [
    {
      "id": "test-time-compute",
      "label": "test-time compute",
      "attention": 14,
      "delta": 13.1,
      "sparkline": [
        6,
        7,
        6,
        6,
        10,
        9,
        8,
        8
      ]
    },
    {
      "id": "agentic-workflows",
      "label": "agentic workflows",
      "attention": 12,
      "delta": 12.3,
      "sparkline": [
        5,
        4,
        4,
        4,
        8,
        8,
        7,
        9
      ]
    },
    {
      "id": "reinforcement-learning",
      "label": "reinforcement learning",
      "attention": 12,
      "delta": 12.4,
      "sparkline": [
        4,
        5,
        5,
        5,
        8,
        8,
        7,
        8
      ]
    },
    {
      "id": "kv-cache",
      "label": "KV cache",
      "attention": 10,
      "delta": 10.2,
      "sparkline": [
        4,
        5,
        4,
        4,
        5,
        5,
        5,
        4
      ]
    },
    {
      "id": "large-language-models",
      "label": "large language models",
      "attention": 10,
      "delta": 10.3,
      "sparkline": [
        5,
        7,
        6,
        6,
        7,
        6,
        6,
        6
      ]
    },
    {
      "id": "routing",
      "label": "routing",
      "attention": 9,
      "delta": 8.8,
      "sparkline": [
        2,
        2,
        2,
        2,
        6,
        6,
        5,
        5
      ]
    },
    {
      "id": "knowledge-distillation",
      "label": "knowledge distillation",
      "attention": 9,
      "delta": 8.7,
      "sparkline": [
        2,
        3,
        2,
        2,
        7,
        7,
        6,
        6
      ]
    },
    {
      "id": "test-time-optimization",
      "label": "test-time optimization",
      "attention": 8,
      "delta": 8,
      "sparkline": [
        0,
        1,
        1,
        1,
        6,
        6,
        5,
        7
      ]
    },
    {
      "id": "ai-agents",
      "label": "AI agents",
      "attention": 7,
      "delta": 2.5,
      "sparkline": [
        3,
        4,
        4,
        4,
        4,
        4,
        4,
        3
      ]
    },
    {
      "id": "context-management",
      "label": "context management",
      "attention": 7,
      "delta": 6.5,
      "sparkline": [
        3,
        3,
        3,
        3,
        3,
        3,
        3,
        3
      ]
    },
    {
      "id": "model-compression",
      "label": "model compression",
      "attention": 7,
      "delta": 6.8,
      "sparkline": [
        0,
        1,
        1,
        1,
        5,
        6,
        6,
        6
      ]
    },
    {
      "id": "diffusion-models",
      "label": "diffusion models",
      "attention": 7,
      "delta": 6.7,
      "sparkline": [
        2,
        2,
        2,
        2,
        3,
        3,
        4,
        5
      ]
    },
    {
      "id": "orchestration",
      "label": "orchestration",
      "attention": 6,
      "delta": 6.1,
      "sparkline": [
        5,
        4,
        4,
        4,
        4,
        3,
        3,
        3
      ]
    },
    {
      "id": "skills",
      "label": "skills",
      "attention": 6,
      "delta": 5.6,
      "sparkline": [
        2,
        3,
        3,
        3,
        2,
        2,
        2,
        2
      ]
    },
    {
      "id": "inference",
      "label": "inference",
      "attention": 6,
      "delta": 6,
      "sparkline": [
        2,
        2,
        2,
        2,
        3,
        3,
        3,
        2
      ]
    },
    {
      "id": "memory-efficiency",
      "label": "memory efficiency",
      "attention": 6,
      "delta": 5.7,
      "sparkline": [
        3,
        3,
        2,
        2,
        2,
        2,
        2,
        2
      ]
    }
  ]
}
