{
  "kind": "technique",
  "horizon": "day",
  "generated": "2026-06-30",
  "synthetic": false,
  "entities": [
    {
      "id": "agentic-workflows",
      "label": "agentic workflows",
      "attention": 3,
      "delta": 3.3,
      "sparkline": [
        10,
        9,
        9,
        8,
        8,
        9,
        8,
        11
      ]
    },
    {
      "id": "ai-agents",
      "label": "AI agents",
      "attention": 3,
      "delta": -0.8,
      "sparkline": [
        22,
        25,
        27,
        29,
        27,
        26,
        29,
        30
      ]
    },
    {
      "id": "uncertainty-quantification",
      "label": "uncertainty quantification",
      "attention": 3,
      "delta": 2.6,
      "sparkline": [
        2,
        3,
        3,
        3,
        3,
        3,
        3,
        6
      ],
      "outlier": {
        "breakout": true,
        "new_entrant": false
      }
    },
    {
      "id": "plan-mode",
      "label": "Plan Mode",
      "attention": 3,
      "delta": 3.3,
      "sparkline": [
        0,
        0,
        0,
        0,
        0,
        0,
        0,
        3
      ],
      "outlier": {
        "breakout": false,
        "new_entrant": true
      }
    },
    {
      "id": "model-context-protocol",
      "label": "Model Context Protocol",
      "attention": 1,
      "delta": 0.9,
      "sparkline": [
        0,
        4,
        4,
        3,
        3,
        3,
        3,
        3
      ]
    },
    {
      "id": "context-management",
      "label": "context management",
      "attention": 1,
      "delta": 0.8,
      "sparkline": [
        7,
        7,
        6,
        6,
        5,
        5,
        5,
        5
      ]
    },
    {
      "id": "persistent-memory",
      "label": "persistent memory",
      "attention": 1,
      "delta": 0.8,
      "sparkline": [
        4,
        4,
        4,
        4,
        3,
        3,
        3,
        4
      ]
    },
    {
      "id": "agent-memory",
      "label": "agent memory",
      "attention": 1,
      "delta": 0.8,
      "sparkline": [
        3,
        3,
        2,
        2,
        2,
        2,
        2,
        2
      ]
    },
    {
      "id": "episodic-memory",
      "label": "episodic memory",
      "attention": 1,
      "delta": 0.1,
      "sparkline": [
        2,
        2,
        2,
        2,
        1,
        1,
        2,
        3
      ]
    }
  ]
}
