{
  "kind": "tool",
  "horizon": "quarter",
  "generated": "2026-06-27",
  "synthetic": false,
  "entities": [
    {
      "id": "ai-agents",
      "label": "AI agents",
      "attention": 520,
      "delta": 514.3,
      "sparkline": [
        190,
        179,
        172,
        183,
        182,
        180,
        177,
        165
      ]
    },
    {
      "id": "code-generation",
      "label": "code generation",
      "attention": 309,
      "delta": 308.7,
      "sparkline": [
        102,
        95,
        94,
        101,
        109,
        106,
        102,
        100
      ]
    },
    {
      "id": "multi-agent-systems",
      "label": "multi-agent systems",
      "attention": 276,
      "delta": 266.7,
      "sparkline": [
        94,
        88,
        88,
        91,
        86,
        81,
        86,
        80
      ]
    },
    {
      "id": "agent-orchestration",
      "label": "agent orchestration",
      "attention": 192,
      "delta": 184.6,
      "sparkline": [
        57,
        53,
        59,
        65,
        61,
        61,
        64,
        59
      ]
    },
    {
      "id": "workflow-automation",
      "label": "workflow automation",
      "attention": 189,
      "delta": 188.5,
      "sparkline": [
        43,
        45,
        46,
        53,
        54,
        54,
        57,
        57
      ]
    },
    {
      "id": "test-time-compute",
      "label": "test-time compute",
      "attention": 188,
      "delta": 177.8,
      "sparkline": [
        72,
        67,
        72,
        68,
        67,
        63,
        62,
        57
      ]
    },
    {
      "id": "multimodal-learning",
      "label": "multimodal learning",
      "attention": 185,
      "delta": 185,
      "sparkline": [
        68,
        63,
        59,
        62,
        65,
        61,
        61,
        61
      ]
    },
    {
      "id": "agentic-workflows",
      "label": "agentic workflows",
      "attention": 173,
      "delta": 167.1,
      "sparkline": [
        44,
        50,
        46,
        52,
        49,
        50,
        53,
        49
      ]
    },
    {
      "id": "video-generation",
      "label": "video generation",
      "attention": 165,
      "delta": 159.8,
      "sparkline": [
        54,
        51,
        48,
        50,
        57,
        53,
        55,
        52
      ]
    },
    {
      "id": "local-inference",
      "label": "local inference",
      "attention": 150,
      "delta": 149.5,
      "sparkline": [
        53,
        49,
        47,
        49,
        56,
        57,
        61,
        56
      ]
    },
    {
      "id": "large-language-models",
      "label": "large language models",
      "attention": 99,
      "delta": 96.9,
      "sparkline": [
        42,
        39,
        37,
        36,
        41,
        39,
        36,
        34
      ]
    },
    {
      "id": "prompt-engineering",
      "label": "prompt engineering",
      "attention": 91,
      "delta": 82.7,
      "sparkline": [
        19,
        18,
        17,
        27,
        30,
        28,
        26,
        29
      ]
    },
    {
      "id": "model-context-protocol",
      "label": "Model Context Protocol",
      "attention": 90,
      "delta": 90.5,
      "sparkline": [
        41,
        38,
        37,
        34,
        32,
        35,
        42,
        39
      ]
    },
    {
      "id": "tool-use",
      "label": "tool use",
      "attention": 74,
      "delta": 74.5,
      "sparkline": [
        22,
        24,
        23,
        25,
        25,
        24,
        30,
        28
      ]
    },
    {
      "id": "model-evaluation",
      "label": "model evaluation",
      "attention": 70,
      "delta": 69.8,
      "sparkline": [
        29,
        32,
        30,
        30,
        29,
        27,
        28,
        26
      ]
    },
    {
      "id": "foundation-models",
      "label": "foundation models",
      "attention": 67,
      "delta": 67,
      "sparkline": [
        25,
        24,
        26,
        25,
        29,
        27,
        29,
        27
      ]
    }
  ]
}
