{
  "id": "continental-vs-maritime-power",
  "label": "continental vs maritime power",
  "aliases": [],
  "kind": "opinion",
  "attention": 5,
  "first_seen": "2026-06-09T18:14:13+00:00",
  "rotation": {
    "horizon": "week",
    "quadrant": "leading",
    "ratio": 145,
    "momentum": 127.1,
    "sparkline": [
      0,
      0,
      0,
      0,
      0,
      0,
      5,
      5
    ]
  },
  "neighbors": [
    {
      "id": "geopolitical-strategy",
      "label": "geopolitical strategy",
      "score": 0.744
    },
    {
      "id": "power-dynamics",
      "label": "power dynamics",
      "score": 0.74
    },
    {
      "id": "territorial-security-doctrine",
      "label": "territorial security doctrine",
      "score": 0.712
    },
    {
      "id": "us-china-competition",
      "label": "US-China competition",
      "score": 0.701
    },
    {
      "id": "labor-leverage",
      "label": "labor leverage",
      "score": 0.686
    },
    {
      "id": "competitive-intelligence",
      "label": "competitive intelligence",
      "score": 0.662
    }
  ],
  "axis_positions": [
    {
      "slug": "open-closed",
      "title": "Open Weights vs Closed and Proprietary",
      "position": -0.819
    },
    {
      "slug": "scaling-efficiency",
      "title": "Scaling and More Compute vs Efficiency and Small Models",
      "position": 0.3
    },
    {
      "slug": "capability-safety",
      "title": "Capabilities vs Safety and Alignment",
      "position": 0.681
    },
    {
      "slug": "research-product",
      "title": "Research and Theory vs Product and Applied",
      "position": 0.097
    },
    {
      "slug": "agents-assistive",
      "title": "Autonomy and Agents vs Assistive and Copilot",
      "position": -0.042
    },
    {
      "slug": "neural-symbolic",
      "title": "End-to-End Neural vs Structured, Symbolic, and Tool-Use",
      "position": 0.261
    },
    {
      "slug": "central-local",
      "title": "Frontier Labs and Centralized vs Local and Community",
      "position": 0.738
    }
  ],
  "top_items": [
    {
      "title": "Sarah Paine - Why Putin and Xi can't escape geography",
      "url": "https://www.youtube.com/watch?v=OS1NZLgKM2c",
      "author_or_channel": "Dwarkesh Patel",
      "published_at": "2026-06-09T18:14:13+00:00",
      "kind": "opinion"
    }
  ]
}
