{
  "id": "elastic-anchoring",
  "label": "elastic anchoring",
  "aliases": [],
  "kind": "technique",
  "attention": 1,
  "first_seen": "2026-06-05T17:53:52Z",
  "rotation": null,
  "neighbors": [
    {
      "id": "non-rigid-deformation",
      "label": "non-rigid deformation",
      "score": 0.768
    },
    {
      "id": "positioning",
      "label": "positioning",
      "score": 0.74
    },
    {
      "id": "subspace-locking",
      "label": "subspace locking",
      "score": 0.737
    },
    {
      "id": "self-forcing",
      "label": "self-forcing",
      "score": 0.728
    },
    {
      "id": "psychological-grounding",
      "label": "psychological grounding",
      "score": 0.726
    },
    {
      "id": "gradient-stability",
      "label": "gradient stability",
      "score": 0.723
    }
  ],
  "axis_positions": [
    {
      "slug": "open-closed",
      "title": "Open Weights vs Closed and Proprietary",
      "position": -0.46
    },
    {
      "slug": "scaling-efficiency",
      "title": "Scaling and More Compute vs Efficiency and Small Models",
      "position": 0.675
    },
    {
      "slug": "capability-safety",
      "title": "Capabilities vs Safety and Alignment",
      "position": 0.124
    },
    {
      "slug": "research-product",
      "title": "Research and Theory vs Product and Applied",
      "position": 0.248
    },
    {
      "slug": "agents-assistive",
      "title": "Autonomy and Agents vs Assistive and Copilot",
      "position": -0.187
    },
    {
      "slug": "neural-symbolic",
      "title": "End-to-End Neural vs Structured, Symbolic, and Tool-Use",
      "position": 0.137
    },
    {
      "slug": "central-local",
      "title": "Frontier Labs and Centralized vs Local and Community",
      "position": 0.13
    }
  ],
  "top_items": [
    {
      "title": "Sparse Subspace-to-Expert Sharing for Task-Agnostic Continual Learning",
      "url": "http://arxiv.org/abs/2606.07500v1",
      "author_or_channel": "Fatema Siddika, Md Anwar Hossen, Tanwi Mallick",
      "published_at": "2026-06-05T17:53:52Z",
      "kind": "technique"
    }
  ]
}
