{
  "id": "hydration",
  "label": "hydration",
  "aliases": [],
  "kind": "tool",
  "attention": 5,
  "first_seen": "2026-04-18T12:01:02+00:00",
  "rotation": null,
  "neighbors": [
    {
      "id": "hydrology",
      "label": "hydrology",
      "score": 0.778
    },
    {
      "id": "adaptation",
      "label": "adaptation",
      "score": 0.764
    },
    {
      "id": "plasticity",
      "label": "plasticity",
      "score": 0.758
    },
    {
      "id": "context-hygiene",
      "label": "context hygiene",
      "score": 0.745
    },
    {
      "id": "consolidation",
      "label": "consolidation",
      "score": 0.743
    },
    {
      "id": "environment-composition",
      "label": "environment composition",
      "score": 0.732
    }
  ],
  "axis_positions": [
    {
      "slug": "open-closed",
      "title": "Open Weights vs Closed and Proprietary",
      "position": 0.107
    },
    {
      "slug": "scaling-efficiency",
      "title": "Scaling and More Compute vs Efficiency and Small Models",
      "position": 0.084
    },
    {
      "slug": "capability-safety",
      "title": "Capabilities vs Safety and Alignment",
      "position": 0.295
    },
    {
      "slug": "research-product",
      "title": "Research and Theory vs Product and Applied",
      "position": 0.325
    },
    {
      "slug": "agents-assistive",
      "title": "Autonomy and Agents vs Assistive and Copilot",
      "position": 0.056
    },
    {
      "slug": "neural-symbolic",
      "title": "End-to-End Neural vs Structured, Symbolic, and Tool-Use",
      "position": 0.092
    },
    {
      "slug": "central-local",
      "title": "Frontier Labs and Centralized vs Local and Community",
      "position": 0.115
    }
  ],
  "top_items": [
    {
      "title": "TanStack Start Full Course 2026 | Build and Deploy a Full Stack Application",
      "url": "https://www.youtube.com/watch?v=Ua__7-x6MWs",
      "author_or_channel": "JavaScript Mastery",
      "published_at": "2026-04-18T12:01:02+00:00",
      "kind": "tool"
    }
  ]
}
