{
  "id": "instruction-following",
  "label": "instruction-following",
  "aliases": [
    "instruction compliance"
  ],
  "kind": "tool",
  "attention": 2,
  "first_seen": "2026-06-06T20:00:00.000Z",
  "rotation": null,
  "neighbors": [
    {
      "id": "attention",
      "label": "attention",
      "score": 0.784
    },
    {
      "id": "embodied-instruction",
      "label": "embodied instruction",
      "score": 0.781
    },
    {
      "id": "skill-learning",
      "label": "skill learning",
      "score": 0.774
    },
    {
      "id": "self-instruct",
      "label": "self-instruct",
      "score": 0.764
    },
    {
      "id": "perception",
      "label": "perception",
      "score": 0.761
    },
    {
      "id": "coordination",
      "label": "coordination",
      "score": 0.761
    }
  ],
  "axis_positions": [
    {
      "slug": "open-closed",
      "title": "Open Weights vs Closed and Proprietary",
      "position": 0.283
    },
    {
      "slug": "scaling-efficiency",
      "title": "Scaling and More Compute vs Efficiency and Small Models",
      "position": -0.083
    },
    {
      "slug": "capability-safety",
      "title": "Capabilities vs Safety and Alignment",
      "position": -0.043
    },
    {
      "slug": "research-product",
      "title": "Research and Theory vs Product and Applied",
      "position": 0.345
    },
    {
      "slug": "agents-assistive",
      "title": "Autonomy and Agents vs Assistive and Copilot",
      "position": -0.094
    },
    {
      "slug": "neural-symbolic",
      "title": "End-to-End Neural vs Structured, Symbolic, and Tool-Use",
      "position": 0.065
    },
    {
      "slug": "central-local",
      "title": "Frontier Labs and Centralized vs Local and Community",
      "position": -0.25
    }
  ],
  "top_items": [
    {
      "title": "GLM-5.2: Built for Long-Horizon Tasks",
      "url": "https://huggingface.co/blog/zai-org/glm-52-blog",
      "author_or_channel": "Hugging Face",
      "published_at": "2026-06-17T09:01:25.000Z",
      "kind": "tool"
    },
    {
      "title": "CoVEBench: Can Video Editing Models Handle Complex Instructions?",
      "url": "https://huggingface.co/papers/2606.08415",
      "author_or_channel": "HF Papers",
      "published_at": "2026-06-06T20:00:00.000Z",
      "kind": "tool"
    }
  ]
}
