{
  "id": "part-aware-representation",
  "label": "part-aware representation",
  "aliases": [],
  "kind": "tool",
  "attention": 1,
  "first_seen": "2026-06-04T17:59:04Z",
  "rotation": {
    "horizon": "week",
    "quadrant": "weakening",
    "ratio": 145,
    "momentum": 70.8,
    "sparkline": [
      0,
      0,
      0,
      1,
      1,
      1,
      1,
      1
    ]
  },
  "neighbors": [
    {
      "id": "omnidirectional-representation",
      "label": "omnidirectional representation",
      "score": 0.76
    },
    {
      "id": "ray-based-representation",
      "label": "ray-based representation",
      "score": 0.728
    },
    {
      "id": "segmentation",
      "label": "segmentation",
      "score": 0.699
    },
    {
      "id": "mixture-density-representation",
      "label": "mixture-density representation",
      "score": 0.685
    },
    {
      "id": "embedding",
      "label": "embedding",
      "score": 0.681
    },
    {
      "id": "sparse-attention",
      "label": "sparse attention",
      "score": 0.671
    }
  ],
  "axis_positions": [
    {
      "slug": "open-closed",
      "title": "Open Weights vs Closed and Proprietary",
      "position": 0.281
    },
    {
      "slug": "scaling-efficiency",
      "title": "Scaling and More Compute vs Efficiency and Small Models",
      "position": 0.02
    },
    {
      "slug": "capability-safety",
      "title": "Capabilities vs Safety and Alignment",
      "position": 0.214
    },
    {
      "slug": "research-product",
      "title": "Research and Theory vs Product and Applied",
      "position": 0.303
    },
    {
      "slug": "agents-assistive",
      "title": "Autonomy and Agents vs Assistive and Copilot",
      "position": -0.013
    },
    {
      "slug": "neural-symbolic",
      "title": "End-to-End Neural vs Structured, Symbolic, and Tool-Use",
      "position": -0.002
    },
    {
      "slug": "central-local",
      "title": "Frontier Labs and Centralized vs Local and Community",
      "position": -0.04
    }
  ],
  "top_items": [
    {
      "title": "PAR3D: A Unified 3D-MLLM with Part-Aware Representation for Scene Understanding",
      "url": "http://arxiv.org/abs/2606.06485v1",
      "author_or_channel": "Shaohui Dai, Yansong Qu, You Shen",
      "published_at": "2026-06-04T17:59:04Z",
      "kind": "tool"
    }
  ]
}
