{
  "id": "refactoring",
  "label": "refactoring",
  "aliases": [
    "code refactoring"
  ],
  "kind": "opinion",
  "attention": 6,
  "first_seen": "2026-06-08T22:10:18.000Z",
  "rotation": {
    "horizon": "week",
    "quadrant": "weakening",
    "ratio": 145,
    "momentum": 70.7,
    "sparkline": [
      0,
      0,
      4,
      4,
      4,
      3,
      3,
      3
    ]
  },
  "neighbors": [
    {
      "id": "debugging",
      "label": "debugging",
      "score": 0.735
    },
    {
      "id": "logic-folding",
      "label": "logic folding",
      "score": 0.72
    },
    {
      "id": "change-enhancement",
      "label": "change enhancement",
      "score": 0.719
    },
    {
      "id": "layout-adjustment",
      "label": "layout adjustment",
      "score": 0.704
    },
    {
      "id": "semantic-purification",
      "label": "semantic purification",
      "score": 0.699
    },
    {
      "id": "abstraction",
      "label": "abstraction",
      "score": 0.698
    }
  ],
  "axis_positions": [
    {
      "slug": "open-closed",
      "title": "Open Weights vs Closed and Proprietary",
      "position": 0.2
    },
    {
      "slug": "scaling-efficiency",
      "title": "Scaling and More Compute vs Efficiency and Small Models",
      "position": -0.435
    },
    {
      "slug": "capability-safety",
      "title": "Capabilities vs Safety and Alignment",
      "position": 0.295
    },
    {
      "slug": "research-product",
      "title": "Research and Theory vs Product and Applied",
      "position": -0.036
    },
    {
      "slug": "agents-assistive",
      "title": "Autonomy and Agents vs Assistive and Copilot",
      "position": -0.2
    },
    {
      "slug": "neural-symbolic",
      "title": "End-to-End Neural vs Structured, Symbolic, and Tool-Use",
      "position": -0.151
    },
    {
      "slug": "central-local",
      "title": "Frontier Labs and Centralized vs Local and Community",
      "position": -0.054
    }
  ],
  "top_items": [
    {
      "title": "The AI Skill I use to prevent refactors",
      "url": "https://www.youtube.com/watch?v=sxAwwvtaFSo",
      "author_or_channel": "JavaScript Mastery",
      "published_at": "2026-06-11T10:40:48+00:00",
      "kind": "opinion"
    },
    {
      "title": "Show HN: Command Center, the AI coding env for people who care about quality",
      "url": "https://www.cc.dev/",
      "author_or_channel": "Darmani",
      "published_at": "2026-06-08T22:10:18.000Z",
      "kind": "tool"
    }
  ]
}
